odoo10_addon_stock_picking_operation_quick_change-10.0.1.0.0.99.dev2-py3.8-nspkg.pth
odoo/addons/stock_picking_operation_quick_change/README.rst
odoo/addons/stock_picking_operation_quick_change/__init__.py
odoo/addons/stock_picking_operation_quick_change/__manifest__.py
odoo/addons/stock_picking_operation_quick_change/i18n/de.po
odoo/addons/stock_picking_operation_quick_change/i18n/es.po
odoo/addons/stock_picking_operation_quick_change/i18n/fr.po
odoo/addons/stock_picking_operation_quick_change/i18n/it.po
odoo/addons/stock_picking_operation_quick_change/i18n/sl.po
odoo/addons/stock_picking_operation_quick_change/i18n/stock_picking_operation_quick_change.pot
odoo/addons/stock_picking_operation_quick_change/static/description/icon.png
odoo/addons/stock_picking_operation_quick_change/static/description/icon.svg
odoo/addons/stock_picking_operation_quick_change/tests/__init__.py
odoo/addons/stock_picking_operation_quick_change/tests/test_stock_picking_operation_quick_change.py
odoo/addons/stock_picking_operation_quick_change/views/stock_picking_view.xml
odoo/addons/stock_picking_operation_quick_change/wizards/__init__.py
odoo/addons/stock_picking_operation_quick_change/wizards/stock_picking_wizard.py
odoo/addons/stock_picking_operation_quick_change/wizards/stock_picking_wizard_view.xml
odoo10_addon_stock_picking_operation_quick_change-10.0.1.0.0.99.dev2.dist-info/METADATA
odoo10_addon_stock_picking_operation_quick_change-10.0.1.0.0.99.dev2.dist-info/WHEEL
odoo10_addon_stock_picking_operation_quick_change-10.0.1.0.0.99.dev2.dist-info/namespace_packages.txt
odoo10_addon_stock_picking_operation_quick_change-10.0.1.0.0.99.dev2.dist-info/top_level.txt
odoo10_addon_stock_picking_operation_quick_change-10.0.1.0.0.99.dev2.dist-info/RECORD
